nmap_mcp/__init__.py
nmap_mcp/__main__.py
nmap_mcp/server.py
nmap_mcp/test.py
mseep_nmap_mcp-0.1.1.dist-info/METADATA
mseep_nmap_mcp-0.1.1.dist-info/WHEEL
mseep_nmap_mcp-0.1.1.dist-info/entry_points.txt
mseep_nmap_mcp-0.1.1.dist-info/licenses/LICENSE
mseep_nmap_mcp-0.1.1.dist-info/RECORD
