Metadata-Version: 2.4
Name: mseep-nmap-mcp
Version: 0.1.1
Summary: A MCP server for nmap network scanning
Author-email: mseep <support@skydeck.ai>
License: MIT
License-File: LICENSE
Requires-Python: >=3.10
Requires-Dist: mcp>=1.4.1
Requires-Dist: python-libnmap>=0.7.2
